<?xml version="1.0" encoding="windows-1251" ?>
<string_table>

	<string id="kat_primary_task">
		<text>ПОДЗЕМЕЛЬЯ</text>
	</string>

	<string id="kat_primary_task_searh_way_out_name">
		<text>Найти выход</text>
	</string>

	<string id="kat_primary_task_searh_way_out_text">
		<text>Нужно как-то отсюда выбираться. Ну и вляпался же я...</text>
	</string>

	<string id="kat_primary_task_search_boss_items_name">
		<text>Найти вещи Хозяина в обвалившейся деревне</text>
	</string>

	<string id="kat_primary_task_search_boss_items_text">
		<text>По словам сталкера, которого я встретил, в обвалившейся деревне есть что-то, что нужно Хозяину подземелий. Кто это, чёрт возьми, такой?</text>
	</string>

	<string id="kat_primary_task_speak_unknown_stalker_name">
		<text>Вернуться к неизвестному сталкеру</text>
	</string>

	<string id="kat_primary_task_speak_unknown_stalker_text">
		<text>Пора вернуться к незнакомцу и разобраться, что делать дальше.</text>
	</string>

	<string id="kat_primary_task_kill_boss_name">
		<text>Найти Хозяина и убить его</text>
	</string>

	<string id="kat_primary_task_kill_boss_text">
		<text>Хозяин подземелий не отпустит меня, пока я не убью его. Осталось только отыскать то место, где он прячется.</text>
	</string>

	<string id="kat_primary_task_final_name">
		<text>Выбраться на поверхность</text>
	</string>

	<string id="kat_primary_task_final_text">
		<text>Вот же тварь попалась. Теперь пора отсюда сваливать.</text>
	</string>

</string_table>
