<?xml version="1.0" encoding="windows-1252" ?>
<string_table>
  <string id="gunsl_wpn_beretta_up_barrel_accuracy_name">
    <text>Laufausrichtung</text>
  </string>
  <string id="gunsl_wpn_beretta_up_barrel_accuracy_descr">
    <text>Erhöht die Schussgenauigkeit.</text>
  </string>
  <string id="gunsl_wpn_beretta_up_barrel_silencer_name">
    <text>Lauf mit Schalldämpfergewinde</text>
  </string>
  <string id="gunsl_wpn_beretta_up_barrel_silencer_descr">
    <text>Ersetzt den Standardlauf durch einen verlängerten Lauf mit Gewinde, wodurch ein Schalldämpfer für das Kaliber 9x19mm angebracht werden kann.</text>
  </string>
  <string id="gunsl_wpn_beretta_up_barrel_bullet_speed_name">
    <text>Lauf nachziehen</text>
  </string>
  <string id="gunsl_wpn_beretta_up_barrel_bullet_speed_descr">
    <text>Durch das nachziehen des Laufs wird die Mündungsgeschwindigkeit erhöht, sowie der Streukreis reduziert.</text>
  </string>
  <string id="gunsl_wpn_beretta_up_pokritie_name">
    <text>Anti-korrosive Innenbeschichtung</text>
  </string>
  <string id="gunsl_wpn_beretta_up_pokritie_descr">
    <text>Das Aufbringen einer speziellen Beschichtung auf die Innenteile trägt dazu bei, den Verschleiß der Waffe zu verlangsamen.</text>
  </string>
  <string id="gunsl_wpn_beretta_up_zapiratel_name">
    <text>Verriegelungsmechanismus einstellen</text>
  </string>
  <string id="gunsl_wpn_beretta_up_zapiratel_descr">
    <text>Erhöht die Mündungsgeschwindigkeit.</text>
  </string>
  <string id="gunsl_wpn_beretta_up_shell_ejector_name">
    <text>Verbesserter Hülsenauswurf</text>
  </string>
  <string id="gunsl_wpn_beretta_up_shell_ejector_descr">
    <text>Ein verbesserter Hülsenauswurf trägt zur Zuverlässigkeit der Waffe bei und reduziert lästige Probleme wie Ladehemmungen.</text>
  </string>
  <string id="gunsl_wpn_beretta_up_sights_name">
    <text>Tritiumeinsätze</text>
  </string>
  <string id="gunsl_wpn_beretta_up_sights_descr">
    <text>Durch die Installation von Leuchteinsätzen im Visier wird die Zielgeschwindigkeit erhöht und das Schießen im Dunkeln erleichtert.</text>
  </string>
  <string id="gunsl_wpn_beretta_up_light_mag_name">
    <text>Leichtes Magazin</text>
  </string>
  <string id="gunsl_wpn_beretta_up_light_mag_descr">
    <text>Durch Ersetzen des Standardmagazins durch ein leichtes und moderneres Fabrikat können Sie das Gewicht der Waffe leicht reduzieren.</text>
  </string>
  <string id="gunsl_wpn_beretta_up_anatomic_handle_name">
    <text>Ergonomischer Griff</text>
  </string>
  <string id="gunsl_wpn_beretta_up_anatomic_handle_descr">
    <text>Kundenspezifische Griffpolster lassen die Waffe besser in der Hand liegen und machen das Zielen und Schießen komfortabler.</text>
  </string>
  <string id="gunsl_wpn_beretta_up_forced_details_name">
    <text>Leichter Abzug</text>
  </string>
  <string id="gunsl_wpn_beretta_up_forced_details_descr">
    <text>Durch die Neukonfiguration des Abzugs lässt sich die Feuerrate erhöhen, was jedoch zu schnellerem Verschleiß der Waffe führt.</text>
  </string>
  <string id="gunsl_wpn_beretta_up_titan_details_name">
    <text>Verstärkte Teile</text>
  </string>
  <string id="gunsl_wpn_beretta_up_titan_details_descr">
    <text>Das Ersetzen von Standardteilen durch Analoga aus hochfesten Legierungen erhöht die Verschleißfestigkeit der Waffe.</text>
  </string>
  <string id="gunsl_wpn_beretta_up_light_details_name">
    <text>Teile aus Leichtmetall</text>
  </string>
  <string id="gunsl_wpn_beretta_up_light_details_descr">
    <text>Der Einbau von Austauschteilen aus Leichtmetall verringert das Gewicht der Waffe.</text>
  </string>
  <string id="gunsl_wpn_beretta_up_spusk_rpm_name">
    <text>Verkürzter Abzugsweg</text>
  </string>
  <string id="gunsl_wpn_beretta_up_spusk_rpm_descr">
    <text>Durch verkürzen des nötigen Abzugswegs wird die Feuergeschwindigkeit erhöht.</text>
  </string>
  <string id="gunsl_wpn_beretta_up_spusk_recoil_name">
    <text>Sanfter Abzug</text>
  </string>
  <string id="gunsl_wpn_beretta_up_spusk_recoil_descr">
    <text>Reduziert den Rückstoß und erhöht die Genauigkeit.</text>
  </string>
  <string id="gunsl_wpn_beretta_up_calibration_name">
    <text>Kalibrierung</text>
  </string>
  <string id="gunsl_wpn_beretta_up_calibration_descr">
    <text>Die individuelle Einstellung und das Auswuchten von Standardpistolenteilen ermöglicht eine höhere Genauigkeit bei gleichzeitiger Reduzierung des Rückstoßes.</text>
  </string>
  <string id="gunsl_wpn_beretta_up_kompensator_name">
    <text>Rückstoßkompensationssystem</text>
  </string>
  <string id="gunsl_wpn_beretta_up_kompensator_descr">
    <text>Reduziert den Rückstoß und macht das Schießen komfortabler.</text>
  </string>
</string_table>
<!--Created/Modified with S.T.A.L.K.E.R. Dialog Extended Editor by Marty Sheppard/ Version: 0.96i ( 2017/02/17) =!!= Last changed: 02.01.2024 18:39:40 -->
