<?xml version="1.0" encoding="windows-1252" ?>
<string_table>
  <string id="gunsl_saiga12_up_barrel_narezka_name">
    <text>Gezogener Lauf</text>
  </string>
  <string id="gunsl_saiga12_up_barrel_narezka_descr">
    <text>Ein gezogener Lauf erhöht die Genauigkeit der Waffe enorm, jedoch kann kein Schrot mehr verschossen werden.</text>
  </string>
  <string id="gunsl_saiga12_up_barrel_dtk_name">
    <text>Mündungskompensator</text>
  </string>
  <string id="gunsl_saiga12_up_barrel_dtk_descr">
    <text>Durch die Installation eines Mündungskompensators wird der Rückstoß verringert.</text>
  </string>
  <string id="gunsl_saiga12_up_sights_name">
    <text>Tritiumeinsätze</text>
  </string>
  <string id="gunsl_saiga12_up_sights_descr">
    <text>Durch die Installation von Leuchteinsätzen im Visier wird die Zielgeschwindigkeit erhöht und das Schießen im Dunkeln erleichtert.</text>
  </string>
  <string id="gunsl_saiga12_up_handle_name">
    <text>Ergonomischer Griff</text>
  </string>
  <string id="gunsl_saiga12_up_handle_descr">
    <text>Bietet einen bequemeren Griff für die rechte Hand.</text>
  </string>
  <string id="gunsl_saiga12_up_titan_details_name">
    <text>Verstärkte Teile</text>
  </string>
  <string id="gunsl_saiga12_up_titan_details_descr">
    <text>Das Ersetzen von Standardteilen durch Analoga aus hochfesten Legierungen erhöht die Verschleißfestigkeit der Waffe.</text>
  </string>
  <string id="gunsl_saiga12_up_lightdetails_name">
    <text>Teile aus Leichtmetall</text>
  </string>
  <string id="gunsl_saiga12_up_lightdetails_descr">
    <text>Der Einbau von Austauschteilen aus Leichtmetall verringert das Gewicht der Waffe.</text>
  </string>
  <string id="gunsl_saiga12_up_light_stock_name">
    <text>Leichter Schaft</text>
  </string>
  <string id="gunsl_saiga12_up_light_stock_descr">
    <text>Das Ersetzen des Standardschafts durch einen leichteren verringert das Gewicht der Waffe.</text>
  </string>
  <string id="gunsl_saiga12_up_stock_nakladka_name">
    <text>Gummierte Rückenplatte</text>
  </string>
  <string id="gunsl_saiga12_up_stock_nakladka_descr">
    <text>Mindert den Rückstoß.</text>
  </string>
  <string id="gunsl_saiga12_up_mag10_name">
    <text>Erweitertes Magazin</text>
  </string>
  <string id="gunsl_saiga12_up_mag10_descr">
    <text>Erweitertes Magazin.</text>
  </string>
  <string id="gunsl_saiga12_up_mag_fix_name">
    <text>Änderung des Patroneneinzugs</text>
  </string>
  <string id="gunsl_saiga12_up_mag_fix_descr">
    <text>Durch die Verfeinerung des Kugelnachschubs kann Ladehemmung entgegengewirkt werden.</text>
  </string>
  <string id="gunsl_saiga12_up_patronnik_name">
    <text>Kammerausrichtung</text>
  </string>
  <string id="gunsl_saiga12_up_patronnik_descr">
    <text>Die sorgfältige Montage der Teile und die Minimierung des Spiels ermöglichen eine höhere Schussgenauigkeit.</text>
  </string>
  <string id="gunsl_saiga12_up_usm_rpm_name">
    <text>Leichter Abzug</text>
  </string>
  <string id="gunsl_saiga12_up_usm_rpm_descr">
    <text>Durch die Modifikation des Abzugs kann die Feuerrate der Waffe erhöht werden.</text>
  </string>
  <string id="gunsl_saiga12_up_light_foregrip_name">
    <text>Leichter Vorderschaft</text>
  </string>
  <string id="gunsl_saiga12_up_light_foregrip_descr">
    <text>Reduziert das Gesamtgewicht der Waffe.</text>
  </string>
  <string id="gunsl_saiga12_up_usm_recoil_name">
    <text>Sanfter Abzug</text>
  </string>
  <string id="gunsl_saiga12_up_usm_recoil_descr">
    <text>Verringert den Rückstoß und erhöht die Genauigkeit.</text>
  </string>
  <string id="gunsl_saiga12_up_accurate_details_name">
    <text>Montagemechanismen</text>
  </string>
  <string id="gunsl_saiga12_up_accurate_details_descr">
    <text>Die Einstellung und sorgfältige Überlappung der Haupteinheiten trägt zur Minimierung des Spiels bei, was sich günstig auf die Schussgenauigkeit auswirkt.</text>
  </string>
</string_table>
<!--Created/Modified with S.T.A.L.K.E.R. Dialog Extended Editor by Marty Sheppard/ Version: 0.96i ( 2017/02/17) =!!= Last changed: 02.01.2024 18:54:00 -->
